temporal_negative_edge_sampler.cpython-310-x86_64-linux-gnu.so
temporal_negative_edge_sampler-0.1.12.dist-info/METADATA
temporal_negative_edge_sampler-0.1.12.dist-info/WHEEL
temporal_negative_edge_sampler-0.1.12.dist-info/top_level.txt
temporal_negative_edge_sampler-0.1.12.dist-info/RECORD
