Metadata-Version: 2.1
Name: temporal-negative-edge-sampler
Version: 0.1.12
Summary: Fast temporal negative edge sampler for graph neural networks
Home-page: https://github.com/ashfaq1701/temporal-negative-edge-sampler
Author: Ashfaq Salehin
Author-email: ashfaq.salehin1701@gmail.com
Requires-Python: >=3.8
Requires-Dist: numpy>=1.19.0
